plaso/__init__.py
plaso/dependencies.py
plaso/analysis/__init__.py
plaso/analysis/browser_search.py
plaso/analysis/chrome_extension.py
plaso/analysis/definitions.py
plaso/analysis/file_hashes.py
plaso/analysis/interface.py
plaso/analysis/logger.py
plaso/analysis/manager.py
plaso/analysis/mediator.py
plaso/analysis/nsrlsvr.py
plaso/analysis/sessionize.py
plaso/analysis/tagging.py
plaso/analysis/unique_domains_visited.py
plaso/analysis/viper.py
plaso/analysis/virustotal.py
plaso/analysis/windows_services.py
plaso/analyzers/__init__.py
plaso/analyzers/hashing_analyzer.py
plaso/analyzers/interface.py
plaso/analyzers/logger.py
plaso/analyzers/manager.py
plaso/analyzers/yara_analyzer.py
plaso/analyzers/hashers/__init__.py
plaso/analyzers/hashers/entropy.py
plaso/analyzers/hashers/interface.py
plaso/analyzers/hashers/manager.py
plaso/analyzers/hashers/md5.py
plaso/analyzers/hashers/sha1.py
plaso/analyzers/hashers/sha256.py
plaso/cli/__init__.py
plaso/cli/extraction_tool.py
plaso/cli/image_export_tool.py
plaso/cli/log2timeline_tool.py
plaso/cli/logger.py
plaso/cli/pinfo_tool.py
plaso/cli/psort_tool.py
plaso/cli/psteal_tool.py
plaso/cli/status_view.py
plaso/cli/storage_media_tool.py
plaso/cli/time_slices.py
plaso/cli/tool_options.py
plaso/cli/tools.py
plaso/cli/views.py
plaso/cli/helpers/__init__.py
plaso/cli/helpers/analysis_plugins.py
plaso/cli/helpers/artifact_definitions.py
plaso/cli/helpers/artifact_filters.py
plaso/cli/helpers/data_location.py
plaso/cli/helpers/database_config.py
plaso/cli/helpers/date_filters.py
plaso/cli/helpers/dynamic_output.py
plaso/cli/helpers/elastic_output.py
plaso/cli/helpers/event_filters.py
plaso/cli/helpers/extraction.py
plaso/cli/helpers/filter_file.py
plaso/cli/helpers/hashers.py
plaso/cli/helpers/interface.py
plaso/cli/helpers/language.py
plaso/cli/helpers/manager.py
plaso/cli/helpers/nsrlsvr_analysis.py
plaso/cli/helpers/output_modules.py
plaso/cli/helpers/parsers.py
plaso-20200717.dist-info/DESCRIPTION.rst
plaso-20200717.dist-info/LICENSE.txt
plaso-20200717.dist-info/METADATA
plaso-20200717.dist-info/RECORD
plaso-20200717.dist-info/WHEEL
plaso-20200717.dist-info/metadata.json
plaso-20200717.dist-info/top_level.txt
