Metadata-Version: 2.0
Name: plaso
Version: 20200717
Summary: Plaso (log2timeline) - Super timeline all the things
Home-page: https://github.com/log2timeline/plaso
Maintainer: Log2Timeline maintainers
Maintainer-email: log2timeline-maintainers@googlegroups.com
License: Apache License, Version 2.0
Platform: UNKNOWN
Classifier: Development Status :: 4 - Beta
Classifier: Environment :: Console
Classifier: Operating System :: OS Independent
Classifier: Programming Language :: Python
